<?xml version="1.0" encoding="UTF-8"?>
<objects serializationModel="Studio.02.02.00">
	<object class="EncodingSetting" id="{45cf96e3-eefe-4439-a4be-b2cf3ae79aed}">
		<property name="encodingFormat">
			<value>3</value>
		</property>
		<property name="quality">
			<value>37</value>
		</property>
		<relationship name="platform">
			<destination>{2bc5bf38-0b1f-4473-80c2-db505d913289}</destination>
		</relationship>
		<relationship name="encodable">
			<destination>{2bc5bf38-0b1f-4473-80c2-db505d913289}</destination>
		</relationship>
	</object>
</objects>
